{
  "id": 10192,
  "title": "Shrek Para Sempre",
  "overview": "Shrek faz um pacto com Rumpelstiltskin para sentir-se como um ogro de verdade novamente, mas ele é enganado e enviado para uma versão distorcida de Tão, Tão Distante - onde Rumpelstiltskin é rei, ogros são caçados, e ele e Fiona nunca se encontraram - ele decide restaurar o seu mundo e recuperar seu verdadeiro amor.",
  "mp4_link": "http://awnagk.gviudclrb.com/vod/9886FC14037C428192FA5ABE59D7800B_media.mp4",
  "poster_path": "/iFXVU0ni6YWgQNSPkoGO1Tk5L3g.jpg",
  "backdrop_path": "/uzzTystB8lL0mRDII5Sfs5HxgkI.jpg",
  "release_date": "2010-05-20",
  "vote_average": 6.406,
  "runtime": 93,
  "genres": [
    "Comédia",
    "Aventura",
    "Fantasia",
    "Animação",
    "Família"
  ],
  "cast": [
    {
      "name": "Mike Myers",
      "character": "Shrek (voice)",
      "profile": "/gjfDl52Kk02MPgUYFjs9bOy33OY.jpg"
    },
    {
      "name": "Eddie Murphy",
      "character": "Donkey (voice)",
      "profile": "/qgjMfefsKwSYsyCaIX46uyOXIpy.jpg"
    },
    {
      "name": "Cameron Diaz",
      "character": "Princess Fiona (voice)",
      "profile": "/tTpQSKwdLrR6xBGHCqg8VcVQZzH.jpg"
    },
    {
      "name": "Antonio Banderas",
      "character": "Puss in Boots (voice)",
      "profile": "/fce7zl6elUzsv7wudHFc7RgFtjD.jpg"
    },
    {
      "name": "Walt Dohrn",
      "character": "Rumpelstiltskin / Priest / Krekraw Ogre (voice)",
      "profile": "/tGWQRNz8T5VNPZgNU2LafpNt2Jn.jpg"
    },
    {
      "name": "Julie Andrews",
      "character": "Queen Lillian (voice)",
      "profile": "/yQ0J92DMiLtQYoytLJ6CuBkdeN0.jpg"
    },
    {
      "name": "John Cleese",
      "character": "King Harold (voice)",
      "profile": "/nQpBf77cStmR35V0XOinm2zZMWG.jpg"
    },
    {
      "name": "Jon Hamm",
      "character": "Brogan (voice)",
      "profile": "/mrXE5fZbEDPc7BEE5G21J6qrwzi.jpg"
    },
    {
      "name": "Jane Lynch",
      "character": "Gretched (voice)",
      "profile": "/nye6D17ZfCHQzr9faYZYyz1CPsZ.jpg"
    },
    {
      "name": "Craig Robinson",
      "character": "Cookie (voice)",
      "profile": "/mTyTrOWUSOBJMOlDpnd4OYx7FlJ.jpg"
    }
  ],
  "trailers": [
    {
      "name": "Shrek Para Sempre",
      "key": "gNRRaQoLguw",
      "site": "YouTube"
    },
    {
      "name": "Shrek Para Sempre - Trailer",
      "key": "TlRgGvROYOM",
      "site": "YouTube"
    }
  ]
}