{
  "id": 12,
  "title": "Procurando Nemo (Finding Nemo)",
  "overview": "Nemo, um jovem peixe-palhaço aventureiro, é inesperadamente levado de sua casa na Grande Barreira de Corais para o aquário do consultório de um dentista. Cabe ao seu preocupado pai Marlin e à simpática mas esquecida peixe Dory trazer Nemo para casa - encontrando tubarões vegetarianos, tartarugas surfistas, medusas hipnóticas, gaivotas esfomeadas e muito mais pelo caminho.",
  "mp4_link": "http://awnagk.gviudclrb.com:80/vod/C1B7331E857449B1AEDF1DB2C9CDB681_media.mp4",
  "poster_path": "/djbivExXSZb0sTO8uYaaQC5vMRM.jpg",
  "backdrop_path": "/eCynaAOgYYiw5yN5lBwz3IxqvaW.jpg",
  "release_date": "2003-05-30",
  "vote_average": 7.82,
  "runtime": 100,
  "genres": [
    "Animação",
    "Família",
    "Aventura"
  ],
  "cast": [
    {
      "name": "Albert Brooks",
      "character": "Marlin (voice)",
      "profile": "/8iDSGu5l93N7benjf6b3AysBore.jpg"
    },
    {
      "name": "Ellen DeGeneres",
      "character": "Dory (voice)",
      "profile": "/z8IEEid4z63CBlJtxrTKEfsW7NA.jpg"
    },
    {
      "name": "Alexander Gould",
      "character": "Nemo (voice)",
      "profile": "/zzfj8LHhSiRntnyThvOBirEEmII.jpg"
    },
    {
      "name": "Willem Dafoe",
      "character": "Gill (voice)",
      "profile": "/ui8e4sgZAwMPi3hzEO53jyBJF9B.jpg"
    },
    {
      "name": "Geoffrey Rush",
      "character": "Nigel (voice)",
      "profile": "/npXFjaFQzBNroCEPllGPTZ5IisA.jpg"
    },
    {
      "name": "Brad Garrett",
      "character": "Bloat (voice)",
      "profile": "/813ffbpoaoaJRdoe1yrbivboWKp.jpg"
    },
    {
      "name": "Allison Janney",
      "character": "Peach (voice)",
      "profile": "/kSaSnQ9xU8eVNL0mTppab95dZA8.jpg"
    },
    {
      "name": "Austin Pendleton",
      "character": "Gurgle (voice)",
      "profile": "/nrXfqtXDDYzSFNLPQnfLkus4I7s.jpg"
    },
    {
      "name": "Stephen Root",
      "character": "Bubbles (voice)",
      "profile": "/2Zwi6AydqQQ9InVdhjYcfJXNzkp.jpg"
    },
    {
      "name": "Vicki Lewis",
      "character": "Deb / Flo (voice)",
      "profile": "/dwTjtleLh1uu8n9AvUCv0n3mi2R.jpg"
    }
  ],
  "trailers": [
    {
      "name": "Procurando Nemo 3D: Trailer Oficial - Disney Pixar",
      "key": "lJhvtAt_1Nk",
      "site": "YouTube"
    }
  ]
}