{
  "id": 14836,
  "title": "Coraline e o Mundo Secreto",
  "overview": "Entediada em sua nova casa, a pequena Coraline descobre uma porta secreta que contém um mundo parecido com o dela, porém melhor em muitas maneiras. Coraline se encanta com a descoberta, mas logo descobre que há algo de errado quando seus pais alternativos tentam mantê-la eternamente nesse mundo paralelo.",
  "mp4_link": "http://awnagk.gviudclrb.com/vod/FA4AB74AB19644B78CB67AFBAD98CFEC_media.mp4",
  "poster_path": "/rranXmvqPT4NoXzmxhFtXr9nNYT.jpg",
  "backdrop_path": "/hofnlIyF6bePkgQOpcuRWLvzf15.jpg",
  "release_date": "2009-02-05",
  "vote_average": 7.921,
  "runtime": 100,
  "genres": [
    "Animação",
    "Família",
    "Fantasia"
  ],
  "cast": [
    {
      "name": "Dakota Fanning",
      "character": "Coraline Jones (voice)",
      "profile": "/hwcO08SVWkelfvgfIa5HsTMxsK8.jpg"
    },
    {
      "name": "Teri Hatcher",
      "character": "Mel Jones / Other Mother (voice)",
      "profile": "/ySmnfZm8ZGabcwp4UwaMDeSzXqx.jpg"
    },
    {
      "name": "Jennifer Saunders",
      "character": "Miss April Spink / Other Spink (voice)",
      "profile": "/pTgxwHcz9L8SNVYvPJS0o0lgHya.jpg"
    },
    {
      "name": "Dawn French",
      "character": "Miss Miriam Forcible / Other Forcible (voice)",
      "profile": "/r6lZgGw4rRRSu6RGfalWh9fJSWM.jpg"
    },
    {
      "name": "Keith David",
      "character": "The Cat (voice)",
      "profile": "/1x0QXavmIy3QmhyrOsV7gMnJaEx.jpg"
    },
    {
      "name": "John Hodgman",
      "character": "Charlie Jones / Other Father (voice)",
      "profile": "/xlgpI6x1OECW6V7uB70DG7BirUa.jpg"
    },
    {
      "name": "Robert Bailey Jr.",
      "character": "Wyborne 'Wybie' Lovat (voice)",
      "profile": "/2CVKz4PSWBXv2IIIX54DW8MVza2.jpg"
    },
    {
      "name": "Ian McShane",
      "character": "Mr. Sergei Alexander Bobinsky / Other Bobinsky (voice)",
      "profile": "/qh9RTLbnr128TZLdGuXwUH9mdBM.jpg"
    },
    {
      "name": "Aankha Neal",
      "character": "Sweet Ghost Girl (voice)",
      "profile": null
    },
    {
      "name": "George Selick",
      "character": "Ghost Boy (voice)",
      "profile": null
    }
  ],
  "trailers": [
    {
      "name": "Filme | Coraline e o Mundo Secreto",
      "key": "qqE2vtPOPXU",
      "site": "YouTube"
    }
  ]
}