{
  "id": 228326,
  "title": "Festa No Céu",
  "overview": "O jovem torero Manolo está dividido entre cumprir as expectativas de sua família ou seguir seu coração e se dedicar à sua verdadeira paixão: a música. Antes de escolher qual caminho seguir, ele embarca numa incrível aventura que o leva a três mundos fantásticos, onde irá enfrentar os seus maiores medos.",
  "mp4_link": "http://awnagk.gviudclrb.com/vod/76EE2C0672754033862AB27783DE7793_media.mp4",
  "poster_path": "/xeYYskD0dABW0drkgvWNIb4OqAy.jpg",
  "backdrop_path": "/b0XkgWgCBurkCZdNXp7kEZdgxEi.jpg",
  "release_date": "2014-10-01",
  "vote_average": 7.532,
  "runtime": 95,
  "genres": [
    "Animação",
    "Família",
    "Fantasia"
  ],
  "cast": [
    {
      "name": "Diego Luna",
      "character": "Manolo (voice)",
      "profile": "/qwbjcyDN37OHiln4a6P4LP31o7F.jpg"
    },
    {
      "name": "Channing Tatum",
      "character": "Joaquin (voice)",
      "profile": "/4TpgnS6l8YUXSne9Av9nda6mjxY.jpg"
    },
    {
      "name": "Zoe Saldaña",
      "character": "Maria (voice)",
      "profile": "/fCJuIn1PMUQtYdRRSnnoZeMJVWs.jpg"
    },
    {
      "name": "Christina Applegate",
      "character": "Mary Beth (voice)",
      "profile": "/ncWS3iguCMCQ53ewacGpMGA6MHv.jpg"
    },
    {
      "name": "Eugenio Derbez",
      "character": "Chato (voice)",
      "profile": "/6o1w3mYF947N6TTakQXcs3NNy4w.jpg"
    },
    {
      "name": "Cheech Marin",
      "character": "Pancho Rodriguez (voice)",
      "profile": "/eecHDNRn9K80ZcuSocsMhQb2G1i.jpg"
    },
    {
      "name": "Gabriel Iglesias",
      "character": "Pepe Rodriguez (voice)",
      "profile": "/8Bjy3RZ5TfNs3oUOUpxTv84G01f.jpg"
    },
    {
      "name": "Ron Perlman",
      "character": "Xibalba (voice)",
      "profile": "/pOgMRdJhbBsvwGLRFXPRASTfcay.jpg"
    },
    {
      "name": "Kate del Castillo",
      "character": "La Muerte (voice)",
      "profile": "/mC9eL2UrGfVQtcf9EvjX0img4Ms.jpg"
    },
    {
      "name": "Ana de la Reguera",
      "character": "Carmen Sánchez (voice)",
      "profile": "/nEacV1wuUHV6eUyErGBhniJ85JY.jpg"
    }
  ],
  "trailers": []
}