{
  "id": 423108,
  "title": "Invocação Do Mal 3: A Ordem Do Demônio",
  "overview": "Um dos casos mais sensacionais de seus arquivos começa com a luta pela alma de um garoto e depois os leva para além de qualquer coisa que já tenham visto. Esse caso marcou a primeira vez na história dos Estados Unidos em que um suspeito de assassinato alegou possessão demoníaca como defesa.",
  "mp4_link": "http://fcoidok.cisantkdh.com/vod/BD621748EA8749CEA7A5922216C55806_media.mp4",
  "poster_path": "/fNu88PdpStJGe09AUYmqTn6NEXB.jpg",
  "backdrop_path": "/p26c040MErns7DJYhisa1CpVB5i.jpg",
  "release_date": "2021-05-25",
  "vote_average": 7.347,
  "runtime": 111,
  "genres": [
    "Terror",
    "Mistério",
    "Thriller"
  ],
  "cast": [
    {
      "name": "Vera Farmiga",
      "character": "Lorraine Warren",
      "profile": "/5Vs7huBmTKftwlsc2BPAntyaQYj.jpg"
    },
    {
      "name": "Patrick Wilson",
      "character": "Ed Warren",
      "profile": "/oym6H2QD9esk4yABjCHaUoNAOa8.jpg"
    },
    {
      "name": "Sterling Jerins",
      "character": "Judy Warren",
      "profile": "/10kkqqbO8Ct58DqsBPSQIsG9ve4.jpg"
    },
    {
      "name": "Sarah Catherine Hook",
      "character": "Debbie Glatzel",
      "profile": "/hLXqA5OZYX9I9BTj82KlVYqgE2i.jpg"
    },
    {
      "name": "Ruairí O'Connor",
      "character": "Arne Cheyne Johnson",
      "profile": "/lSnYC598qzvh20VfSDOa3tpcLBo.jpg"
    },
    {
      "name": "Julian Hilliard",
      "character": "David Glatzel",
      "profile": "/lp1IJliBZb9OFP5KK09HjSGOsau.jpg"
    },
    {
      "name": "Charlene Amoia",
      "character": "Judy Glatzel",
      "profile": "/8hJNPw3XCErifcZZPOfd20JmiTC.jpg"
    },
    {
      "name": "John Noble",
      "character": "Father Kastner",
      "profile": "/t9dB8uU27sQDaEEFMiQvp5sbrXU.jpg"
    },
    {
      "name": "Eugenie Bondurant",
      "character": "The Occultist",
      "profile": "/9ULAELEKNha7VCJhRWoer58NcJe.jpg"
    },
    {
      "name": "Shannon Kook",
      "character": "Drew Thomas",
      "profile": "/rCTdLWbrqsGbMml8TNfGD94jPpp.jpg"
    }
  ],
  "trailers": [
    {
      "name": "INVOCAÇÃO DO MAL 3: A ORDEM DO DEMÔNIO - Trailer Oficial",
      "key": "anDtrp34xig",
      "site": "YouTube"
    }
  ]
}